.MFLOWGEN_TOP
.gitattributes
.gitignore
.readthedocs.yaml
.travis.yml
LICENSE
MANIFEST.in
README.md
configure
.github/workflows/pytest-ci.yml
adks/freepdk-45nm/README.md
adks/freepdk-45nm/configure.yml
adks/freepdk-45nm/pkgs/.gitignore
adks/freepdk-45nm/pkgs/base/adk.tcl
adks/freepdk-45nm/pkgs/base/klayout.lyp
adks/freepdk-45nm/pkgs/base/rtk-tech.info
adks/freepdk-45nm/pkgs/base/rtk-tech.lef
adks/freepdk-45nm/pkgs/base/rtk-tech.par
adks/freepdk-45nm/pkgs/base/stdcells.gds
adks/freepdk-45nm/pkgs/base/stdcells.lef
adks/freepdk-45nm/pkgs/base/stdcells.lib
adks/freepdk-45nm/pkgs/base/stdcells.v
adks/freepdk-45nm/view-tiny/adk.tcl
adks/freepdk-45nm/view-tiny/klayout.lyp
adks/freepdk-45nm/view-tiny/rtk-tech.info
adks/freepdk-45nm/view-tiny/rtk-tech.lef
adks/freepdk-45nm/view-tiny/rtk-tech.par
adks/freepdk-45nm/view-tiny/stdcells.gds
adks/freepdk-45nm/view-tiny/stdcells.lef
adks/freepdk-45nm/view-tiny/stdcells.lib
adks/freepdk-45nm/view-tiny/stdcells.v
adks/skywater-130nm/README.md
adks/skywater-130nm/configure.yml
designs/GcdUnit/.mflowgen.yml
designs/GcdUnit/construct-commercial-full.py
designs/GcdUnit/construct-commercial.py
designs/GcdUnit/construct-open.py
designs/GcdUnit/orfs-design/configure.yml
designs/GcdUnit/orfs-design/orfs-design/nangate45/gcd/config.mk
designs/GcdUnit/orfs-design/orfs-design/nangate45/gcd/constraint.sdc
designs/GcdUnit/orfs-design/orfs-design/nangate45/gcd/metadata-base-ok.json
designs/GcdUnit/orfs-design/orfs-design/nangate45/gcd/rules-base.json
designs/GcdUnit/orfs-design/orfs-design/src/gcd/README.md
designs/GcdUnit/orfs-design/orfs-design/src/gcd/gcd.v
designs/GcdUnit/rtl/GcdUnit-demo.v
designs/GcdUnit/rtl/configure.yml
designs/GcdUnit/rtl/outputs/design.v
designs/GcdUnit/testbench/GcdUnitTb.sv
designs/GcdUnit/testbench/configure.yml
designs/GcdUnit/testbench/generate_test_vectors.py
designs/GcdUnit/testbench/readme.md
designs/GcdUnit/testbench/outputs/design.args
docs/.gitignore
docs/Makefile
docs/api-edge.rst
docs/api-graph.rst
mflowgen.egg-info/PKG-INFO
mflowgen.egg-info/SOURCES.txt
mflowgen.egg-info/dependency_links.txt
mflowgen.egg-info/entry_points.txt
mflowgen.egg-info/requires.txt
mflowgen.egg-info/top_level.txt
mflowgen-0.7.0.dist-info/LICENSE
mflowgen-0.7.0.dist-info/METADATA
mflowgen-0.7.0.dist-info/WHEEL
mflowgen-0.7.0.dist-info/entry_points.txt
mflowgen-0.7.0.dist-info/top_level.txt
mflowgen-0.7.0.dist-info/RECORD
