Metadata-Version: 2.1
Name: mflowgen
Version: 0.7.0
Summary: mflowgen: A Modular ASIC and FPGA Flow Generator
Home-page: https://github.com/mflowgen/mflowgen
Author: Christopher Torng
Author-email: clt67@cornell.edu
License: BSD
Platform: UNKNOWN
Classifier: Development Status :: 4 - Beta
Classifier: License :: OSI Approved :: BSD License
Classifier: Programming Language :: Python :: 3 :: Only
Classifier: Operating System :: MacOS :: MacOS X
Classifier: Operating System :: POSIX :: Linux
Classifier: Environment :: Console
Classifier: Topic :: Scientific/Engineering :: Electronic Design Automation (EDA)
Classifier: Topic :: Software Development :: Build Tools
Requires-Python: >=3.7
License-File: LICENSE
Requires-Dist: pytest >=4.4
Requires-Dist: pyyaml >=5.0
